momaland/__init__.py
momaland/envs/__init__.py
momaland/envs/beach/__init__.py
momaland/envs/beach/beach.py
momaland/envs/beach/mobeach_v0.py
momaland/envs/breakthrough/__init__.py
momaland/envs/breakthrough/breakthrough.py
momaland/envs/breakthrough/breakthrough_check.py
momaland/envs/breakthrough/mobreakthrough_v0.py
momaland/envs/connect4/__init__.py
momaland/envs/connect4/connect4.py
momaland/envs/connect4/connect4_check.py
momaland/envs/connect4/moconnect4_v0.py
momaland/envs/crazyrl/__init__.py
momaland/envs/crazyrl/crazyRL_base.py
momaland/envs/crazyrl/gl_utils.py
momaland/envs/crazyrl/catch/__init__.py
momaland/envs/crazyrl/catch/catch.py
momaland/envs/crazyrl/catch/catch_v0.py
momaland/envs/crazyrl/escort/__init__.py
momaland/envs/crazyrl/escort/escort.py
momaland/envs/crazyrl/escort/escort_v0.py
momaland/envs/crazyrl/surround/__init__.py
momaland/envs/crazyrl/surround/surround.py
momaland/envs/crazyrl/surround/surround_v0.py
momaland/envs/gem_mining/__init__.py
momaland/envs/gem_mining/gem_mining.py
momaland/envs/gem_mining/mogem_mining_v0.py
momaland/envs/ingenious/__init__.py
momaland/envs/ingenious/ingenious.py
momaland/envs/ingenious/ingenious_base.py
momaland/envs/ingenious/ingenious_check.py
momaland/envs/ingenious/ingenious_seedtest.py
momaland/envs/ingenious/moingenious_v0.py
momaland/envs/item_gathering/__init__.py
momaland/envs/item_gathering/asset_utils.py
momaland/envs/item_gathering/item_gathering.py
momaland/envs/item_gathering/map_utils.py
momaland/envs/item_gathering/moitem_gathering_v0.py
momaland/envs/item_gathering/assets/agent.png
momaland/envs/item_gathering/assets/item.png
momaland/envs/item_gathering/assets/map_bg1.png
momaland/envs/item_gathering/assets/map_bg2.png
momaland/envs/multiwalker_stability/__init__.py
momaland/envs/multiwalker_stability/momultiwalker_stability.py
momaland/envs/multiwalker_stability/momultiwalker_stability_base.py
momaland/envs/multiwalker_stability/momultiwalker_stability_v0.py
momaland-0.2.0.dist-info/licenses/LICENSE
momaland-0.2.0.dist-info/METADATA
momaland-0.2.0.dist-info/WHEEL
momaland-0.2.0.dist-info/top_level.txt
momaland-0.2.0.dist-info/RECORD
