Metadata-Version: 2.4
Name: momaland
Version: 0.2.0
Summary: A standard API for Multi-Objective Multi-Agent Decision making and a diverse set of reference environments.
Author: Umut Ucak
Author-email: Florian Felten <florian.felten@uni.lu>, Hicham Azmani <hicham.azmani@vub.be>, Roxana Radulescu <r.t.radulescu@uu.nl>, "Hendrik J. S. Baier" <h.j.s.baier@tue.nl>, Willem Röpke <willem.ropke@vub.be>, Patrick Mannion <patrick.mannion@universityofgalway.ie>, "Diederik M. Roijers" <diederik.roijers@vub.be>
License: GNU General Public License v3.0
Project-URL: Homepage, https://github.com/rradules/momaland/tree/main
Project-URL: Repository, https://github.com/rradules/momaland/tree/main
Project-URL: Documentation, https://github.com/rradules/momaland/tree/main
Project-URL: Bug Report, https://github.com/rradules/momaland/tree/main/issues
Keywords: Reinforcement Learning,Multi-Objective,Multi-Agent,RL,AI,gymnasium,pettingzoo
Classifier: Development Status :: 4 - Beta
Classifier: License :: OSI Approved :: MIT License
Classifier: Programming Language :: Python :: 3
Classifier: Programming Language :: Python :: 3.9
Classifier: Programming Language :: Python :: 3.10
Classifier: Programming Language :: Python :: 3.11
Classifier: Programming Language :: Python :: 3.12
Classifier: Intended Audience :: Science/Research
Classifier: Topic :: Scientific/Engineering :: Artificial Intelligence
Requires-Python: >=3.9
License-File: LICENSE
Requires-Dist: gymnasium>=1.1.0
Requires-Dist: pettingzoo[butterfly,sisl]>=1.24.0
Requires-Dist: numpy>=1.21.0
Requires-Dist: networkx>=3.1
Requires-Dist: sympy>=1.12
Requires-Dist: pygame>=2.6.0
Requires-Dist: PyOpenGL>=3.1.6
Requires-Dist: PyOpenGL-accelerate>=3.1.1
Requires-Dist: pillow>=8.3.1
Requires-Dist: wandb>=0.16.1
Provides-Extra: learning
Requires-Dist: jax>=0.4.13; extra == "learning"
Requires-Dist: chex>=0.1; extra == "learning"
Requires-Dist: distrax>=0.1.3; extra == "learning"
Requires-Dist: flax>=0.6; extra == "learning"
Requires-Dist: optax>=0.1; extra == "learning"
Requires-Dist: orbax-checkpoint>=0.2.3; extra == "learning"
Requires-Dist: chex>=0.1; extra == "learning"
Requires-Dist: etils>=1.3; extra == "learning"
Requires-Dist: supersuit>=3.9; extra == "learning"
Requires-Dist: tqdm>=4.66.1; extra == "learning"
Requires-Dist: pandas>=2.0.3; extra == "learning"
Requires-Dist: matplotlib>=3.7.4; extra == "learning"
Requires-Dist: morl_baselines[all]; extra == "learning"
Requires-Dist: pycddlib==2.1.6; extra == "learning"
Provides-Extra: all
Requires-Dist: jax>=0.4.13; extra == "all"
Requires-Dist: chex>=0.1; extra == "all"
Requires-Dist: distrax>=0.1.3; extra == "all"
Requires-Dist: flax>=0.6; extra == "all"
Requires-Dist: optax>=0.1; extra == "all"
Requires-Dist: orbax-checkpoint>=0.2.3; extra == "all"
Requires-Dist: chex>=0.1; extra == "all"
Requires-Dist: etils>=1.3; extra == "all"
Requires-Dist: supersuit>=3.9; extra == "all"
Requires-Dist: tqdm>=4.66.1; extra == "all"
Requires-Dist: pandas>=2.0.3; extra == "all"
Requires-Dist: matplotlib>=3.7.4; extra == "all"
Requires-Dist: morl_baselines[all]; extra == "all"
Requires-Dist: pycddlib==2.1.6; extra == "all"
Provides-Extra: testing
Requires-Dist: pytest==7.1.3; extra == "testing"
Dynamic: license-file
